[
   {
      "title": "SWING",
      "description": "Delux whisky reserve ",
      "price": 23780,
      "img": "https://i.ibb.co/3Bhwm06/img-swing.png",
      "code": "cod001",
      "stock": 34,
      "id": 1
   },
   {
      "title": "Gin",
      "description": "Bebida apta para mayores de 18 a単os",
      "code": "123fdadsas",
      "price": 12000,
      "status": true,
      "stock": 25,
      "category": "bebida alcoholica",
      "thumbnails": "#",
      "id": 2
   },
   {
      "title": "Tequila",
      "description": "Bebida apta para mayores de 18 a単os",
      "code": "123241adsas",
      "price": 12000,
      "status": true,
      "stock": 25,
      "category": "bebida alcoholica",
      "thumbnails": "#",
      "id": 3
   },
   {
      "title": "Cerveza",
      "description": "Bebida apta para mayores de 18 a単os",
      "code": "123241adsas",
      "price": 12000,
      "status": true,
      "stock": 25,
      "category": "bebida alcoholica",
      "thumbnails": "#",
      "id": 4
   },
   {
      "title": "Absenta",
      "description": "Bebida apta para mayores de 18 a単os",
      "code": "123241adsas",
      "price": 12000,
      "status": true,
      "stock": 25,
      "category": "bebida alcoholica",
      "thumbnails": "#",
      "id": 5
   }
]